celai_chatwoot/__init__.py
celai_chatwoot/connector/__init__.py
celai_chatwoot/connector/bot_utils.py
celai_chatwoot/connector/model/__init__.py
celai_chatwoot/connector/model/woot_attachment.py
celai_chatwoot/connector/model/woot_lead.py
celai_chatwoot/connector/model/woot_message.py
celai_chatwoot/connector/msg_utils.py
celai_chatwoot/connector/sample_data/incoming_img_msg_from_web.json
celai_chatwoot/connector/sample_data/incoming_text_msg_from_web.json
celai_chatwoot/connector/woo_connector.py
celai_chatwoot-0.2.1.dist-info/METADATA
celai_chatwoot-0.2.1.dist-info/WHEEL
celai_chatwoot-0.2.1.dist-info/RECORD
