Metadata-Version: 2.1
Name: celai-chatwoot
Version: 0.2.1
Summary: 
Author: Alex Martin
Author-email: alejamp@gmail.com
Requires-Python: >=3.11,<4.0
Classifier: License :: OSI Approved :: MIT License
Classifier: Operating System :: OS Independent
Classifier: Programming Language :: Python :: 3
Classifier: Programming Language :: Python :: 3.11
Classifier: Programming Language :: Python :: 3.12
Classifier: Programming Language :: Python :: 3.13
Requires-Dist: aiohttp (>=3.9.5)
Requires-Dist: celai (>=0.3.35)
Requires-Dist: filetype (>=1.2.0)
Project-URL: Homepage, https://github.com/cel-ai/celai-chatwoot
Project-URL: Issues, https://github.com/cel-ai/celai-chatwoot/issues
